{
  "stats": {
    "suites": 1,
    "tests": 3,
    "passes": 3,
    "pending": 0,
    "failures": 0,
    "start": "2021-11-29T14:47:20.896Z",
    "end": "2021-11-29T14:49:57.576Z",
    "duration": 156680,
    "testsRegistered": 3,
    "passPercent": 100,
    "pendingPercent": 0,
    "other": 0,
    "hasOther": false,
    "skipped": 0,
    "hasSkipped": false
  },
  "results": [
    {
      "uuid": "8c688986-c7b0-4a5e-bfb4-940bb8be25d4",
      "title": "",
      "fullFile": "",
      "file": "",
      "beforeHooks": [],
      "afterHooks": [],
      "tests": [],
      "suites": [
        {
          "uuid": "c6164115-8f96-489a-a430-be5f76f2f381",
          "title": "Tests",
          "fullFile": "D:\\TPKS\\Thesis\\test\\tests.js",
          "file": "\\test\\tests.js",
          "beforeHooks": [],
          "afterHooks": [],
          "tests": [
            {
              "title": "Page Navigation",
              "fullTitle": "Tests Page Navigation",
              "timedOut": false,
              "duration": 35389,
              "state": "passed",
              "speed": "slow",
              "pass": true,
              "fail": false,
              "pending": false,
              "context": null,
              "code": "const driver = await new Builder().forBrowser('chrome').build();\nawait driver.manage().window().maximize();\nawait driver.get('https://ruslanpleskun.github.io/cstd-pleskunruslan-2122/');\nawait driver.findElement(By.id('season')).click();\nawait driver.sleep(3000);\nawait driver.findElement(By.id('homes')).click();\nawait driver.sleep(3000);\nawait driver.findElement(By.id('character-profiles')).click();\nawait driver.sleep(3000);\nawait driver.findElement(By.id('homes')).click();\nawait driver.sleep(3000);\nawait driver.findElement(By.id('webshops')).click();\nawait driver.sleep(3000);\nawait driver.findElement(By.id('homes')).click();\nawait driver.sleep(3000);\nawait driver.navigate().refresh();\nawait driver.findElement(By.id('season')).click();\nawait driver.sleep(3000);\nawait driver.findElement(By.id('character-profiles')).click();\nawait driver.sleep(3000);\nawait driver.findElement(By.id('webshops')).click();\nawait driver.sleep(3000);\nawait driver.findElement(By.id('homes')).click();\nawait driver.sleep(3000);\nawait driver.navigate().refresh();\nawait driver.quit();",
              "err": {},
              "uuid": "f46b696d-16ff-4048-b26c-0070b4cabb98",
              "parentUUID": "c6164115-8f96-489a-a430-be5f76f2f381",
              "isHook": false,
              "skipped": false
            },
            {
              "title": "Links and slides",
              "fullTitle": "Tests Links and slides",
              "timedOut": false,
              "duration": 47644,
              "state": "passed",
              "speed": "slow",
              "pass": true,
              "fail": false,
              "pending": false,
              "context": null,
              "code": "const driver = await new Builder().forBrowser('chrome').build();\nawait driver.manage().window().maximize();\nawait driver.get('https://ruslanpleskun.github.io/cstd-pleskunruslan-2122/');\nawait driver.findElement(By.id('season')).click();\nawait driver.sleep(3000);\nawait driver.findElement(By.css(\"a[title='Rick and Morty']\")).click();\nawait driver.sleep(3000);\nawait driver.navigate().back();\nawait driver.navigate().refresh();\nawait driver.findElement(By.linkText('United States')).click();\nawait driver.sleep(3000);\nawait driver.navigate().back();\nawait driver.navigate().refresh();\nawait driver.findElement(By.xpath(\"//section[@id='seasons']/article[@class='season']//a[@title='Cartoon Network']\")).click();\nawait driver.sleep(3000);\nawait driver.navigate().back();\nawait driver.findElement(By.xpath(\"//section[@id='seasons']/article[@class='season']//a[@title='Adult Swim']\")).click();\nawait driver.sleep(3000);\nawait driver.navigate().back();\nawait driver.findElement(By.xpath(\"//section[@id='seasons']/article[@class='season']//a[@title='Pilot (Rick and Morty)']\")).click();\nawait driver.sleep(3000);\nawait driver.navigate().back();\nawait driver.navigate().refresh();\nawait driver.findElement(By.xpath(\"//button[@class='next']\")).click();\nawait driver.sleep(3000);\nawait driver.findElement(By.xpath(\"//button[@class='prev']\")).click();\nawait driver.sleep(3000);\nawait driver.findElement(By.css('video')).click();\nawait driver.sleep(10000);\nawait driver.findElement(By.css('video')).click();\nawait driver.sleep(3000);\nawait driver.quit();",
              "err": {},
              "uuid": "68a1dcb4-c279-4071-9c6f-d0309b20dced",
              "parentUUID": "c6164115-8f96-489a-a430-be5f76f2f381",
              "isHook": false,
              "skipped": false
            },
            {
              "title": "Buttons",
              "fullTitle": "Tests Buttons",
              "timedOut": false,
              "duration": 73638,
              "state": "passed",
              "speed": "slow",
              "pass": true,
              "fail": false,
              "pending": false,
              "context": null,
              "code": "const driver = await new Builder().forBrowser('chrome').build();\nawait driver.manage().window().maximize();\nawait driver.get('https://ruslanpleskun.github.io/cstd-pleskunruslan-2122/');\nawait driver.findElement(By.id('webshops')).click();\nawait driver.sleep(3000);\nawait driver.findElement(By.css('section:nth-of-type(1) > .order-button')).click();\nawait driver.sleep(3000);\nawait driver.navigate().back();\nawait driver.sleep(3000);\nawait driver.navigate().refresh();\nawait driver.findElement(By.xpath(\"//section[@id='webshop']/article/section[2]/button[@class='order-button']\")).click();\nawait driver.sleep(3000);\nawait driver.navigate().back();\nawait driver.findElement(By.css('section:nth-of-type(3) > .order-button')).click();\nawait driver.sleep(3000);\nawait driver.navigate().back();\nawait driver.sleep(3000);\nawait driver.findElement(By.xpath(\"//section[@id='webshop']/article/section[4]/button[@class='order-button']\")).click();\nawait driver.sleep(3000);\nawait driver.navigate().back();\nawait driver.findElement(By.css('section:nth-of-type(5) > .order-button')).click();\nawait driver.sleep(3000);\nawait driver.navigate().back();\nawait driver.sleep(3000);\nawait driver.navigate().refresh();\nawait driver.findElement(By.xpath(\"//section[@id='webshop']/article/section[6]/button[@class='order-button']\")).click();\nawait driver.sleep(3000);\nawait driver.navigate().back();\nawait driver.findElement(By.css('section:nth-of-type(7) > .order-button')).click();\nawait driver.sleep(3000);\nawait driver.navigate().back();\nawait driver.sleep(3000);\nawait driver.findElement(By.xpath(\"//section[@id='webshop']/article/section[8]/button[@class='order-button']\")).click();\nawait driver.sleep(3000);\nawait driver.navigate().back();\nawait driver.findElement(By.css('section:nth-of-type(9) > .order-button')).click();\nawait driver.sleep(3000);\nawait driver.navigate().back();\nawait driver.navigate().refresh();\nawait driver.sleep(3000);\nawait driver.quit();",
              "err": {},
              "uuid": "e8e72057-95da-4e19-ba2d-efa6cfc6e851",
              "parentUUID": "c6164115-8f96-489a-a430-be5f76f2f381",
              "isHook": false,
              "skipped": false
            }
          ],
          "suites": [],
          "passes": [
            "f46b696d-16ff-4048-b26c-0070b4cabb98",
            "68a1dcb4-c279-4071-9c6f-d0309b20dced",
            "e8e72057-95da-4e19-ba2d-efa6cfc6e851"
          ],
          "failures": [],
          "pending": [],
          "skipped": [],
          "duration": 156671,
          "root": false,
          "rootEmpty": false,
          "_timeout": 0
        }
      ],
      "passes": [],
      "failures": [],
      "pending": [],
      "skipped": [],
      "duration": 0,
      "root": true,
      "rootEmpty": true,
      "_timeout": 0
    }
  ],
  "meta": {
    "mocha": {
      "version": "9.1.3"
    },
    "mochawesome": {
      "options": {
        "quiet": false,
        "reportFilename": "testReport",
        "saveHtml": true,
        "saveJson": true,
        "consoleReporter": "spec",
        "useInlineDiffs": false,
        "code": true
      },
      "version": "7.0.1"
    },
    "marge": {
      "options": {
        "reportDir": "testReport",
        "reportFilename": "testReport"
      },
      "version": "6.0.1"
    }
  }
}